k7eel/__init__.py
k7eel/main.py
woowoowo-0.1.1.dist-info/METADATA
woowoowo-0.1.1.dist-info/WHEEL
woowoowo-0.1.1.dist-info/entry_points.txt
woowoowo-0.1.1.dist-info/top_level.txt
woowoowo-0.1.1.dist-info/RECORD
